wirepickle/__init__.py
wirepickle/client.py
wirepickle/server.py
wirepickle-1.0.1.dist-info/METADATA
wirepickle-1.0.1.dist-info/WHEEL
wirepickle-1.0.1.dist-info/top_level.txt
wirepickle-1.0.1.dist-info/RECORD
