Metadata-Version: 2.1
Name: wirepickle
Version: 1.0.1
Summary: Effortless Python RPC with ZeroMQ
Home-page: https://github.com/pkage/wirepickle
Author: Patrick Kage
Author-email: patrick.r.kage@gmail.com
License: MIT
Platform: UNKNOWN
Requires-Dist: termcolor
Requires-Dist: pyzmq
